shelllangchain/__init__.py
shelllangchain/langchain_bash_helper.py
shelllangchain-0.2.2.dist-info/LICENSE
shelllangchain-0.2.2.dist-info/METADATA
shelllangchain-0.2.2.dist-info/WHEEL
shelllangchain-0.2.2.dist-info/entry_points.txt
shelllangchain-0.2.2.dist-info/top_level.txt
shelllangchain-0.2.2.dist-info/RECORD
