Metadata-Version: 2.1
Name: shelllangchain
Version: 0.2.2
Summary: Natural language to shell command converter
Home-page: https://github.com/belda/shelllangchain
Author: Belda
Author-email: jakub.belescak@centrum.cz
Classifier: Programming Language :: Python :: 3
Classifier: License :: OSI Approved :: MIT License
Classifier: Operating System :: OS Independent
Requires-Python: >=3.4
License-File: LICENSE
Requires-Dist: wheel
Requires-Dist: requests
Requires-Dist: langchain
Requires-Dist: openai
Requires-Dist: pyperclip
Requires-Dist: python-dotenv
